feistpy/__init__.py
feistpy/dataset.py
feistpy/sampler.py
feistpy-1.1.2.dist-info/METADATA
feistpy-1.1.2.dist-info/WHEEL
feistpy-1.1.2.dist-info/top_level.txt
feistpy-1.1.2.dist-info/RECORD
