Metadata-Version: 2.1
Name: feistpy
Version: 1.1.2
Summary: Fiestel sampling for PyTorch
Requires-Python: >=3.8
Requires-Dist: pygfc ~=1.0.5
Provides-Extra: test
Requires-Dist: pytest ~=7.4.3 ; extra == 'test'
Requires-Dist: torch ; extra == 'test'
Requires-Dist: numpy ; extra == 'test'
